py_html/__init__.py
py_html/contrib/__init__.py
py_html/contrib/bootstrap/__init__.py
py_html/contrib/bootstrap/_types.py
py_html/contrib/bootstrap/alert.py
py_html/contrib/bootstrap/avatar.py
py_html/contrib/bootstrap/badge.py
py_html/contrib/bootstrap/breadcrumb.py
py_html/contrib/bootstrap/button.py
py_html/contrib/bootstrap/card.py
py_html/contrib/bootstrap/icon.py
py_html/contrib/bootstrap/layout_grid_system.py
py_html/contrib/bootstrap/main.py
py_html/contrib/bootstrap/util.py
py_html/el/__init__.py
py_html/el/base.py
py_html/el/elements/__init__.py
py_html/el/elements/audio.py
py_html/el/elements/basic.py
py_html/el/elements/formatting.py
py_html/el/elements/forms.py
py_html/el/elements/frames.py
py_html/el/elements/images.py
py_html/el/elements/links.py
py_html/el/elements/lists.py
py_html/el/elements/meta_info.py
py_html/el/elements/programming.py
py_html/el/elements/semantics.py
py_html/el/elements/tables.py
py_html/styles/__init__.py
py_html/styles/base.py
py_html/styles/spec.py
py_html/styles/utils.py
py_htmlbuilder-0.1.2.dist-info/WHEEL
py_htmlbuilder-0.1.2.dist-info/METADATA
py_htmlbuilder-0.1.2.dist-info/RECORD
