Metadata-Version: 2.1
Name: py-htmlbuilder
Version: 0.1.2
Summary: PyHTMLBuilder is HTML in python objects
Author-email: Ezeudoh Tochukwu <tochukwu.ezeudoh@gmail.com>
Requires-Python: >=3.8
Classifier: Intended Audience :: Information Technology
Classifier: Intended Audience :: System Administrators
Classifier: Operating System :: OS Independent
Classifier: Topic :: Internet
Classifier: Topic :: Software Development :: Libraries :: Application Frameworks
Classifier: Topic :: Software Development :: Libraries :: Python Modules
Classifier: Topic :: Software Development :: Libraries
Classifier: Topic :: Software Development
Classifier: Typing :: Typed
Classifier: Environment :: Web Environment
Classifier: Intended Audience :: Developers
Classifier: License :: OSI Approved :: MIT License
Classifier: Programming Language :: Python :: 3
Classifier: Programming Language :: Python :: 3.8
Classifier: Programming Language :: Python :: 3.9
Classifier: Programming Language :: Python :: 3.10
Classifier: Programming Language :: Python :: 3.11
Classifier: Programming Language :: Python :: 3 :: Only
Classifier: Framework :: AsyncIO
Classifier: Topic :: Internet :: WWW/HTTP :: HTTP Servers
Classifier: Topic :: Internet :: WWW/HTTP
Project-URL: Bug Tracker, https://github.com/python-ellar/py-htmlbuilder/issues
Project-URL: Documentation, https://python-ellar.github.io/py-htmlbuilder/
Project-URL: Homepage, https://python-ellar.github.io/py-htmlbuilder/
Project-URL: Source, https://github.com/python-ellar/py-htmlbuilder
Provides-Extra: all
